{"name":"create a new meeting in StartSharp","id":"create-a-meeting;create-a-new-meeting-in-startsharp","testSteps":[{"number":1,"description":"Example #1: {user\u003dadmin, password\u003dserenity}","duration":33609,"startTime":"2022-08-23T19:50:19.138-05:00[America/Bogota]","screenshots":[{"screenshot":"621c42e1092b9e7552dea1415a1ac628498c14ea6d5e298bbe7d02060bcf5838.png","timeStamp":1661302252747}],"result":"SUCCESS","precondition":false,"level":0,"children":[{"number":2,"description":"Kevin open up","duration":7510,"startTime":"2022-08-23T19:50:19.564-05:00[America/Bogota]","screenshots":[{"screenshot":"751298964d54efe821e38c398502db5185a4645fe7bc134e2de78e4b6043083d.png","timeStamp":1661302227074}],"result":"SUCCESS","precondition":false,"level":1,"children":[{"number":3,"description":"Kevin opens the Start sharp page","duration":7444,"startTime":"2022-08-23T19:50:19.617-05:00[America/Bogota]","screenshots":[{"screenshot":"751298964d54efe821e38c398502db5185a4645fe7bc134e2de78e4b6043083d.png","timeStamp":1661302227060}],"result":"SUCCESS","precondition":false,"level":2}]},{"number":4,"description":"Given login page with my credentials\r\n| user | password |\r\n| admin | serenity |","duration":2093,"startTime":"2022-08-23T19:50:27.075-05:00[America/Bogota]","screenshots":[{"screenshot":"0a4dca28e3ead8de5a32ae5678ae17f54838f4ba62d923557011b0128709dddb.png","timeStamp":1661302229168}],"result":"SUCCESS","precondition":false,"level":1,"children":[{"number":5,"description":"Kevin sing in","duration":1873,"startTime":"2022-08-23T19:50:27.291-05:00[America/Bogota]","screenshots":[{"screenshot":"0a4dca28e3ead8de5a32ae5678ae17f54838f4ba62d923557011b0128709dddb.png","timeStamp":1661302229164}],"result":"SUCCESS","precondition":false,"level":2,"children":[{"number":6,"description":"Kevin enters DELETE into write user","duration":440,"startTime":"2022-08-23T19:50:27.322-05:00[America/Bogota]","screenshots":[{"screenshot":"f08beb52fb1ac3a65d67938c33c82fe5cd4267e3eed5dc6e2f59b01bcbc3dd4d.png","timeStamp":1661302227762}],"result":"SUCCESS","precondition":false,"level":3},{"number":7,"description":"Kevin enters DELETE into write password","duration":236,"startTime":"2022-08-23T19:50:27.765-05:00[America/Bogota]","screenshots":[{"screenshot":"1d6084441e948de1e8780e0d37c5ece85f9d43cfe835dae1957f2974b6ccccce.png","timeStamp":1661302228001}],"result":"SUCCESS","precondition":false,"level":3},{"number":8,"description":"Kevin enters \u0027admin\u0027 into write user","duration":413,"startTime":"2022-08-23T19:50:28.017-05:00[America/Bogota]","screenshots":[{"screenshot":"4ddec2d37d405a660e71b0fb78ac79b914a84109c3bdb3503201b79ca1b5a15d.png","timeStamp":1661302228430}],"result":"SUCCESS","precondition":false,"level":3},{"number":9,"description":"Kevin enters \u0027serenity\u0027 into write password","duration":403,"startTime":"2022-08-23T19:50:28.434-05:00[America/Bogota]","screenshots":[{"screenshot":"c274dbc17a5c3b8382b185472922abe7e0b8a7d37e85670c4d85321f2afaa66d.png","timeStamp":1661302228837}],"result":"SUCCESS","precondition":false,"level":3},{"number":10,"description":"Kevin clicks on click Sing In","duration":315,"startTime":"2022-08-23T19:50:28.846-05:00[America/Bogota]","screenshots":[{"screenshot":"0a4dca28e3ead8de5a32ae5678ae17f54838f4ba62d923557011b0128709dddb.png","timeStamp":1661302229161}],"result":"SUCCESS","precondition":false,"level":3}]}]},{"number":11,"description":"When create a new organization business unit on the page\r\n| organization |\r\n| choucair |","duration":5989,"startTime":"2022-08-23T19:50:29.168-05:00[America/Bogota]","screenshots":[{"screenshot":"701b5841ff2ee398e382077b2e8e2c0c96ea7dceeb20d01bb2bece94aa96239c.png","timeStamp":1661302235157}],"result":"SUCCESS","precondition":false,"level":1,"children":[{"number":12,"description":"Kevin create new organization","duration":5975,"startTime":"2022-08-23T19:50:29.181-05:00[America/Bogota]","screenshots":[{"screenshot":"701b5841ff2ee398e382077b2e8e2c0c96ea7dceeb20d01bb2bece94aa96239c.png","timeStamp":1661302235156}],"result":"SUCCESS","precondition":false,"level":2,"children":[{"number":13,"description":"Kevin clicks on click organization","duration":2921,"startTime":"2022-08-23T19:50:29.207-05:00[America/Bogota]","screenshots":[{"screenshot":"cb5a37ab8babaee6c6eeaaf80ddd3b82f47d489cfdb235973598a37ed2515f08.png","timeStamp":1661302232128}],"result":"SUCCESS","precondition":false,"level":3},{"number":14,"description":"Kevin clicks on click business unit","duration":881,"startTime":"2022-08-23T19:50:32.131-05:00[America/Bogota]","screenshots":[{"screenshot":"6237511de531d2c191cdabed273e02b0a62b934d9d81c6eb7113040c05f3bc30.png","timeStamp":1661302233012}],"result":"SUCCESS","precondition":false,"level":3},{"number":15,"description":"Kevin clicks on click new business unit","duration":707,"startTime":"2022-08-23T19:50:33.014-05:00[America/Bogota]","screenshots":[{"screenshot":"1a3cc280849e844dfddb3a20c875ddb610a670b811a504e119ad75cee60010a1.png","timeStamp":1661302233721}],"result":"SUCCESS","precondition":false,"level":3},{"number":16,"description":"Kevin enters \u0027choucair\u0027 into write business unit","duration":356,"startTime":"2022-08-23T19:50:33.730-05:00[America/Bogota]","screenshots":[{"screenshot":"6de4ef632d8443e68bda90c80238f3b83ff5ca0d87b1381603bf5adc5eae8433.png","timeStamp":1661302234085}],"result":"SUCCESS","precondition":false,"level":3},{"number":17,"description":"Kevin clicks on toggle parent business unit","duration":552,"startTime":"2022-08-23T19:50:34.087-05:00[America/Bogota]","screenshots":[{"screenshot":"b64e9b588a0ddfb815a7a48069129fb00444f8478c3f7df2ced4dfd2a92da305.png","timeStamp":1661302234639}],"result":"SUCCESS","precondition":false,"level":3},{"number":18,"description":"Kevin clicks on select parent business unit","duration":246,"startTime":"2022-08-23T19:50:34.641-05:00[America/Bogota]","screenshots":[{"screenshot":"6979842b5b735420a3e689785df872a18bf1d9a5f8e099b19e074e02253ff313.png","timeStamp":1661302234886}],"result":"SUCCESS","precondition":false,"level":3},{"number":19,"description":"Kevin clicks on save business unit","duration":264,"startTime":"2022-08-23T19:50:34.889-05:00[America/Bogota]","screenshots":[{"screenshot":"701b5841ff2ee398e382077b2e8e2c0c96ea7dceeb20d01bb2bece94aa96239c.png","timeStamp":1661302235153}],"result":"SUCCESS","precondition":false,"level":3}]}]},{"number":20,"description":"And Create a new meeting\r\n| meeting | number |\r\n| choucair testing | 548646 |","duration":15777,"startTime":"2022-08-23T19:50:35.157-05:00[America/Bogota]","screenshots":[{"screenshot":"23ae948f798ab8cc8f5c1a678f4ac58daecce7458e9f7865933c4fe6ed97fbf2.png","timeStamp":1661302250934}],"result":"SUCCESS","precondition":false,"level":1,"children":[{"number":21,"description":"Kevin create meeting","duration":15763,"startTime":"2022-08-23T19:50:35.169-05:00[America/Bogota]","screenshots":[{"screenshot":"23ae948f798ab8cc8f5c1a678f4ac58daecce7458e9f7865933c4fe6ed97fbf2.png","timeStamp":1661302250932}],"result":"SUCCESS","precondition":false,"level":2,"children":[{"number":22,"description":"Kevin clicks on click meeting","duration":546,"startTime":"2022-08-23T19:50:35.195-05:00[America/Bogota]","screenshots":[{"screenshot":"475946359e20afb4ec9201f483ca013866358d9dbb1297a4a9c50cd8fc81b3c6.png","timeStamp":1661302235741}],"result":"SUCCESS","precondition":false,"level":3},{"number":23,"description":"Kevin clicks on click meetings","duration":2389,"startTime":"2022-08-23T19:50:35.744-05:00[America/Bogota]","screenshots":[{"screenshot":"1268e3825d402debb18dbdc33649b73e2604bf9fe8747120066022d55e4294a7.png","timeStamp":1661302238133}],"result":"SUCCESS","precondition":false,"level":3},{"number":24,"description":"Kevin clicks on click new meeting","duration":770,"startTime":"2022-08-23T19:50:38.135-05:00[America/Bogota]","screenshots":[{"screenshot":"f871703bd5ce66f8ac521d6d94a9321f7d44ec9d629ffef7b5bb1586c33f37b8.png","timeStamp":1661302238905}],"result":"SUCCESS","precondition":false,"level":3},{"number":25,"description":"Kevin enters \u0027choucair testing\u0027 into write name meeting","duration":407,"startTime":"2022-08-23T19:50:38.910-05:00[America/Bogota]","screenshots":[{"screenshot":"393028a0b580b00183f3edd3f542d99ac6eb7e29da7db19c4dc62139f1d91f27.png","timeStamp":1661302239317}],"result":"SUCCESS","precondition":false,"level":3},{"number":26,"description":"Kevin enters \u0027548646\u0027 into write number meeting","duration":440,"startTime":"2022-08-23T19:50:39.336-05:00[America/Bogota]","screenshots":[{"screenshot":"70032f98d79aa807b846977c66f46bda36615b75af5fea8478809cbf6b7d6dd8.png","timeStamp":1661302239776}],"result":"SUCCESS","precondition":false,"level":3},{"number":27,"description":"Kevin clicks on toggle type meeting","duration":386,"startTime":"2022-08-23T19:50:39.778-05:00[America/Bogota]","screenshots":[{"screenshot":"16a63effaa2034116363cf1d2b3057c7633fdccaa6289932309a99305a69e5ed.png","timeStamp":1661302240164}],"result":"SUCCESS","precondition":false,"level":3},{"number":28,"description":"Kevin clicks on select type meeting","duration":275,"startTime":"2022-08-23T19:50:40.167-05:00[America/Bogota]","screenshots":[{"screenshot":"b2cd82b678b2817f0d8802c6342499bbd28d2a1785e4fa9c16bd187d3a58d306.png","timeStamp":1661302240442}],"result":"SUCCESS","precondition":false,"level":3},{"number":29,"description":"Kevin clicks on click calendar button","duration":435,"startTime":"2022-08-23T19:50:40.444-05:00[America/Bogota]","screenshots":[{"screenshot":"e6e64e3c91d7e59eb39e97656a97a031a1d4ed8ea1d5ad00878796d651209965.png","timeStamp":1661302240879}],"result":"SUCCESS","precondition":false,"level":3},{"number":30,"description":"Kevin clicks on Select start day the meeting","duration":322,"startTime":"2022-08-23T19:50:40.880-05:00[America/Bogota]","screenshots":[{"screenshot":"6c914e5723c04c41d2ff9aedcf2a89731ea7705b1199633f261483b13c83e601.png","timeStamp":1661302241202}],"result":"SUCCESS","precondition":false,"level":3},{"number":31,"description":"Kevin clicks on Select start hour the meeting","duration":275,"startTime":"2022-08-23T19:50:41.204-05:00[America/Bogota]","screenshots":[{"screenshot":"cf843e80de7222dccd24dc9d5d31bf9d14be2bafa8eea63e9327a34fdf3d0a94.png","timeStamp":1661302241479}],"result":"SUCCESS","precondition":false,"level":3},{"number":32,"description":"Kevin clicks on click calendar button","duration":395,"startTime":"2022-08-23T19:50:41.480-05:00[America/Bogota]","screenshots":[{"screenshot":"96a5c444679902579f93635200a1bb717239a7a4b99b4bab066a58447a18f997.png","timeStamp":1661302241875}],"result":"SUCCESS","precondition":false,"level":3},{"number":33,"description":"Kevin clicks on Select end day the meeting","duration":293,"startTime":"2022-08-23T19:50:41.877-05:00[America/Bogota]","screenshots":[{"screenshot":"6ef1aa011c5dfca0a3793cfe3a0381c7a4275b6680585de11f5441fd589398e4.png","timeStamp":1661302242169}],"result":"SUCCESS","precondition":false,"level":3},{"number":34,"description":"Kevin clicks on select hour end meeting","duration":294,"startTime":"2022-08-23T19:50:42.199-05:00[America/Bogota]","screenshots":[{"screenshot":"8f83e0c4cb566f4c72d915b543368bbddc0a25863f0a78378d8afdfb78a5f6b9.png","timeStamp":1661302242493}],"result":"SUCCESS","precondition":false,"level":3},{"number":35,"description":"Kevin clicks on click toggle location","duration":338,"startTime":"2022-08-23T19:50:42.495-05:00[America/Bogota]","screenshots":[{"screenshot":"55b08f5be5ba189859069f072580e114191cecd30d6d466834c990d9bbfd3702.png","timeStamp":1661302242833}],"result":"SUCCESS","precondition":false,"level":3},{"number":36,"description":"Kevin clicks on Select toggle location","duration":271,"startTime":"2022-08-23T19:50:42.837-05:00[America/Bogota]","screenshots":[{"screenshot":"1db9387e5ab8a3bfa77619c739534abc815215642b7b2b00b5c7d02d40e8bac1.png","timeStamp":1661302243108}],"result":"SUCCESS","precondition":false,"level":3},{"number":37,"description":"Kevin clicks on click toggle unit","duration":295,"startTime":"2022-08-23T19:50:43.110-05:00[America/Bogota]","screenshots":[{"screenshot":"bc909a1276edd8bd933d329cdd31ce67195a97b427aa7ec0d6e71b3699d40a66.png","timeStamp":1661302243405}],"result":"SUCCESS","precondition":false,"level":3},{"number":38,"description":"Kevin clicks on Select unit","duration":253,"startTime":"2022-08-23T19:50:43.406-05:00[America/Bogota]","screenshots":[{"screenshot":"8bad60f4cddecc16637b94fd838793b79c3ff7ce693605e4a61a5bda7eea92ba.png","timeStamp":1661302243659}],"result":"SUCCESS","precondition":false,"level":3},{"number":39,"description":"Kevin clicks on click toggle Organized by","duration":366,"startTime":"2022-08-23T19:50:43.661-05:00[America/Bogota]","screenshots":[{"screenshot":"9f7191403c73fb242e7cdc6047640dc5b245b40ae670a7911eb187369e00f86c.png","timeStamp":1661302244027}],"result":"SUCCESS","precondition":false,"level":3},{"number":40,"description":"Kevin clicks on Select Select Organized By","duration":258,"startTime":"2022-08-23T19:50:44.029-05:00[America/Bogota]","screenshots":[{"screenshot":"6871cda6f04d4120a09cfca2a1c28f239216bfe8d2bf94d080ddd131bf0a1d8b.png","timeStamp":1661302244287}],"result":"SUCCESS","precondition":false,"level":3},{"number":41,"description":"Kevin clicks on click toggle reporter","duration":321,"startTime":"2022-08-23T19:50:44.288-05:00[America/Bogota]","screenshots":[{"screenshot":"de5569860e244d1875a7ba1882472ab5f98dec3da30e685ebb29b4ed71cd780b.png","timeStamp":1661302244608}],"result":"SUCCESS","precondition":false,"level":3},{"number":42,"description":"Kevin clicks on Select Select reporter","duration":262,"startTime":"2022-08-23T19:50:44.610-05:00[America/Bogota]","screenshots":[{"screenshot":"f7c6b8e5870fb7650b6d6c9529f9ddf335715f5d02e078b3de1e3a45ef1044a4.png","timeStamp":1661302244872}],"result":"SUCCESS","precondition":false,"level":3},{"number":43,"description":"Kevin clicks on click toggle Attendee List","duration":316,"startTime":"2022-08-23T19:50:44.873-05:00[America/Bogota]","screenshots":[{"screenshot":"fa453dba7ba717611e71a58be9ae8621dd3c7b07752864db632c2e82b44cc14b.png","timeStamp":1661302245189}],"result":"SUCCESS","precondition":false,"level":3},{"number":44,"description":"Kevin clicks on Select Select Attender","duration":295,"startTime":"2022-08-23T19:50:45.191-05:00[America/Bogota]","screenshots":[{"screenshot":"9049d8d40d5109f8f5994ef6f2e655859017742d577efc9a9ce13e44e6d343c8.png","timeStamp":1661302245486}],"result":"SUCCESS","precondition":false,"level":3},{"number":45,"description":"Kevin clicks on save meeting","duration":308,"startTime":"2022-08-23T19:50:45.488-05:00[America/Bogota]","screenshots":[{"screenshot":"8b5fe5817267ed2a4c3edec608e03c7c5b6bdb05cc3702bd282dcf7899e18ce2.png","timeStamp":1661302245796}],"result":"SUCCESS","precondition":false,"level":3}]}]},{"number":46,"description":"Then verify that the meeting was created with the name of choucair testing","duration":1808,"startTime":"2022-08-23T19:50:50.935-05:00[America/Bogota]","screenshots":[{"screenshot":"621c42e1092b9e7552dea1415a1ac628498c14ea6d5e298bbe7d02060bcf5838.png","timeStamp":1661302252743}],"result":"SUCCESS","precondition":false,"level":1,"children":[{"number":47,"description":"Then review name the meeting","duration":1584,"startTime":"2022-08-23T19:50:51.157-05:00[America/Bogota]","screenshots":[{"screenshot":"621c42e1092b9e7552dea1415a1ac628498c14ea6d5e298bbe7d02060bcf5838.png","timeStamp":1661302252741}],"result":"SUCCESS","precondition":false,"level":2,"children":[{"number":48,"description":"Kevin clicks on click toggle Meeting type ","duration":342,"startTime":"2022-08-23T19:50:51.164-05:00[America/Bogota]","screenshots":[{"screenshot":"fe0cfeba0fd19e6b4c40cf34e71217c1ed3ded25f022d000a5af4ab6eb0560e2.png","timeStamp":1661302251506}],"result":"SUCCESS","precondition":false,"level":3},{"number":49,"description":"Kevin clicks on click toggle Meeting type ","duration":288,"startTime":"2022-08-23T19:50:51.507-05:00[America/Bogota]","screenshots":[{"screenshot":"137751fd3d9573373a1ac91893c3af6f9168588cf7cfc32adecac2937f21d55a.png","timeStamp":1661302251795}],"result":"SUCCESS","precondition":false,"level":3},{"number":50,"description":"Kevin clicks on  search meeting ","duration":936,"startTime":"2022-08-23T19:50:51.800-05:00[America/Bogota]","screenshots":[{"screenshot":"621c42e1092b9e7552dea1415a1ac628498c14ea6d5e298bbe7d02060bcf5838.png","timeStamp":1661302252736}],"result":"SUCCESS","precondition":false,"level":3}]}]}]}],"userStory":{"id":"create-a-meeting","storyName":"Create a meeting","path":"src/test/resources/features/escenary1.feature","narrative":"  As a user, I want to be able to create a meeting in StartSharp","type":"feature"},"featureTag":{"name":"Features/Create a meeting","type":"feature","displayName":"Features/Create a meeting"},"title":"create a new meeting in StartSharp","tags":[{"name":"Create a meeting","type":"feature","displayName":"Create a meeting"},{"name":"scenery","type":"tag","displayName":"scenery"}],"startTime":"2022-08-23T19:50:18.973-05:00[America/Bogota]","duration":35824,"projectKey":"","dataTable":{"headers":["user","password"],"rows":[{"values":["admin","serenity"],"result":"SUCCESS"}],"predefinedRows":true,"scenarioOutline":"Given login page with my credentials\n\rWhen create a new organization business unit on the page\n\rAnd Create a new meeting\n\rThen verify that the meeting was created with the name of choucair testing\n\r","dataSetDescriptors":[{"startRow":0,"rowCount":0,"name":""}]},"manual":false,"testSource":"Cucumber","actors":[{"name":"Kevin","can":["browse the web"]}],"result":"SUCCESS","scenarioOutline":"Given login page with my credentials\r\n|user | password|\r\n|\u003cuser\u003e | \u003cpassword\u003e|\r\nWhen create a new organization business unit on the page\r\n|organization|\r\n|choucair|\r\nAnd Create a new meeting\r\n|meeting | number|\r\n|choucair testing | 548646|\r\nThen verify that the meeting was created with the name of choucair testing"}